coscine/__about__.py
coscine/__init__.py
coscine/__main__.py
coscine/client.py
coscine/common.py
coscine/exceptions.py
coscine/metadata.py
coscine/project.py
coscine/py.typed
coscine/resource.py
coscine-0.11.12.dist-info/licenses/LICENSE.txt
coscine-0.11.12.dist-info/METADATA
coscine-0.11.12.dist-info/WHEEL
coscine-0.11.12.dist-info/top_level.txt
coscine-0.11.12.dist-info/RECORD
