Metadata-Version: 2.4
Name: coscine
Version: 0.11.12
Summary: The Coscine Python SDK provides a pythonic high-level interface to the Coscine REST API.
Home-page: https://git.rwth-aachen.de/coscine/community-features/coscine-python-sdk
Author: RWTH Aachen University
Author-email: coscine@itc.rwth-aachen.de
License: MIT License
Project-URL: Issues, https://git.rwth-aachen.de/coscine/community-features/coscine-python-sdk/-/issues
Project-URL: Documentation, https://coscine.pages.rwth-aachen.de/community-features/coscine-python-sdk/
Keywords: Coscine,RWTH Aachen,Research Data Management
Classifier: Programming Language :: Python :: 3.10
Classifier: Programming Language :: Python :: 3.11
Classifier: Programming Language :: Python :: 3.12
Classifier: Programming Language :: Python :: 3.13
Classifier: License :: OSI Approved :: MIT License
Classifier: Operating System :: OS Independent
Classifier: Topic :: Scientific/Engineering
Classifier: Topic :: Software Development
Classifier: Topic :: Software Development :: Libraries :: Python Modules
Classifier: Intended Audience :: Science/Research
Classifier: Intended Audience :: Developers
Classifier: Development Status :: 5 - Production/Stable
Classifier: Typing :: Typed
Requires-Python: >=3.10
License-File: LICENSE.txt
Requires-Dist: boto3
Requires-Dist: isodate
Requires-Dist: pyshacl
Requires-Dist: rdflib
Requires-Dist: requests
Requires-Dist: requests-cache
Requires-Dist: requests-toolbelt
Requires-Dist: tabulate
Requires-Dist: tqdm
Dynamic: author
Dynamic: author-email
Dynamic: classifier
Dynamic: description
Dynamic: description-content-type
Dynamic: home-page
Dynamic: keywords
Dynamic: license
Dynamic: license-file
Dynamic: project-url
Dynamic: requires-dist
Dynamic: requires-python
Dynamic: summary
